bits/__init__.py
bits/mx/__init__.py
bits/mx/gnarwl.py
bits/mx/google.py
bits/mx/groups.py
bits/mx/localmail.py
bits/mx/nicknames.py
bits/mx/update.py
bits_mx-1.1.2.dist-info/METADATA
bits_mx-1.1.2.dist-info/WHEEL
bits_mx-1.1.2.dist-info/RECORD
